LICENSE
MANIFEST.in
README.md
pyproject.toml
requirements.txt
setup.cfg
setup.py
EnhancedDockerMake.egg-info/PKG-INFO
EnhancedDockerMake.egg-info/SOURCES.txt
EnhancedDockerMake.egg-info/dependency_links.txt
EnhancedDockerMake.egg-info/entry_points.txt
EnhancedDockerMake.egg-info/requires.txt
EnhancedDockerMake.egg-info/top_level.txt
dockermake/__init__.py
dockermake/__main__.py
dockermake/builds.py
dockermake/cli.py
dockermake/errors.py
dockermake/imagedefs.py
dockermake/staging.py
dockermake/step.py
dockermake/utils.py
example/DockerMake.yml
example/sample_data/airline_data/AirPassengers.csv
example/sample_data/plant_growth/Puromycin.csv
img/step1.png
img/step2.png
test/test_errors.py
test/test_example.py
test/test_features.py